blades/__init__.py
blades/train.py
blades/adversaries/__init__.py
blades/adversaries/adaptive_adversary.py
blades/adversaries/adversary.py
blades/adversaries/alie_adversary.py
blades/adversaries/attackclippedclustering_adversary.py
blades/adversaries/ipm_adversary.py
blades/adversaries/labelflip_adversary.py
blades/adversaries/minmax_adversary.py
blades/adversaries/noise_adversary.py
blades/adversaries/signflip_adversary.py
blades/adversaries/signguard_adversary.py
blades/adversaries/tests/__init__.py
blades/adversaries/tests/test_adaptive_attack.py
blades/adversaries/tests/test_adversary.py
blades/adversaries/tests/test_labelflip_adversary.py
blades/adversaries/tests/test_noise_adversary.py
blades/algorithms/__init__.py
blades/algorithms/registry.py
blades/algorithms/fedavg/__init__.py
blades/algorithms/fedavg/fedavg.py
blades/algorithms/fedavg/fedavg_dp.py
blades/algorithms/fedavg/tests/__init__.py
blades/algorithms/fedavg/tests/test_fedavg.py
blades/benchmarks/main.py
blades/clients/__init__.py
blades/clients/callbacks.py
blades/clients/client.py
blades/clients/dp_client.py
blades/tuned_examples/fedavg_60_mnist.yaml
blades/tuned_examples/fedavg_cifar10_resnet_noniid.yaml
blades/tuned_examples/fedavg_dp.yaml
blades/tuned_examples/fedavg_fashion_cnn_noniid.yaml
blades/tuned_examples/fedavg_fashion_mnist.yaml
blades/tuned_examples/fedavg_resnet_cifar10.yaml
blades/tuned_examples/fedavg_toy_mnist.yaml
blades/tuned_examples/fedavg_ucihar.yaml
blades/tuned_examples/fedsgd_cifar10.yaml
blades/tuned_examples/fedsgd_cnn_fashion_mnist.yaml
blades/tuned_examples/fedsgd_ucihar.yaml
blades/tuned_examples/local20_cnn_FashionMNIST.yaml
blades/tuned_examples/local20_resnet_cifar10.yaml
blades-0.1.1234.dist-info/entry_points.txt
blades-0.1.1234.dist-info/LICENSE
blades-0.1.1234.dist-info/WHEEL
blades-0.1.1234.dist-info/METADATA
blades-0.1.1234.dist-info/RECORD
