Metadata-Version: 2.1
Name: blades
Version: 0.1.1234
Summary: A Unified Benchmark Suite for Byzantine Attacks and Defenses in Federated Learning
Keywords: deep-learning,pytorch,federated-learning
Author-email: Shenghui Li <shenghui.li@it.uu.se>
Requires-Python: >=3.9
Classifier: Development Status :: 5 - Production/Stable
Classifier: License :: OSI Approved :: Apache Software License
Classifier: Programming Language :: Python
Classifier: Programming Language :: Python :: 3.8
Classifier: Programming Language :: Python :: 3.9
Classifier: Programming Language :: Python :: 3.10
Classifier: Programming Language :: Python :: 3.11
Classifier: Programming Language :: Python :: 3 :: Only
Requires-Dist: torch>=2.0.1
Requires-Dist: torchvision~=0.15.2
Requires-Dist: torchaudio
Requires-Dist: numpy>=1.26.1
Requires-Dist: ray>=2.8.0
Requires-Dist: matplotlib>=3.8.1
Requires-Dist: requests>=2.27.1
Requires-Dist: setuptools
Requires-Dist: ruamel.yaml
Requires-Dist: tqdm
Requires-Dist: wandb>=0.15.12
Requires-Dist: typer
Requires-Dist: dm_tree
Requires-Dist: scikit-learn>=1.3.2
Requires-Dist: pytest
Requires-Dist: ray[rllib]
Requires-Dist: pre-commit
Requires-Dist: torchmetrics
Project-URL: repository, https://github.com/lishenghui/blades
